mediapipe-0.10.18.dist-info/RECORD
mediapipe-0.10.18.dist-info/WHEEL
mediapipe-0.10.18.dist-info/top_level.txt
mediapipe-0.10.18.dist-info/METADATA
mediapipe-0.10.18.dist-info/LICENSE
mediapipe/__init__.py
mediapipe/framework/calculator_pb2.py
mediapipe/framework/mediapipe_options_pb2.py
mediapipe/framework/status_handler_pb2.py
mediapipe/framework/test_calculators_pb2.py
mediapipe/framework/thread_pool_executor_pb2.py
mediapipe/framework/calculator_options_pb2.py
mediapipe/framework/packet_factory_pb2.py
mediapipe/framework/stream_handler_pb2.py
mediapipe/framework/calculator_profile_pb2.py
mediapipe/framework/packet_generator_pb2.py
mediapipe/framework/__init__.py
mediapipe/framework/formats/classification_pb2.py
mediapipe/framework/formats/matrix_data_pb2.py
mediapipe/framework/formats/detection_pb2.py
mediapipe/framework/formats/rect_pb2.py
mediapipe/framework/formats/image_format_pb2.py
mediapipe/framework/formats/landmark_pb2.py
mediapipe/framework/formats/time_series_header_pb2.py
mediapipe/framework/formats/image_file_properties_pb2.py
mediapipe/framework/formats/affine_transform_data_pb2.py
mediapipe/framework/formats/body_rig_pb2.py
mediapipe/framework/formats/__init__.py
mediapipe/framework/formats/location_data_pb2.py
mediapipe/framework/formats/motion/optical_flow_field_data_pb2.py
mediapipe/framework/formats/motion/__init__.py
mediapipe/framework/formats/annotation/rasterization_pb2.py
mediapipe/framework/formats/annotation/locus_pb2.py
mediapipe/framework/formats/annotation/__init__.py
mediapipe/framework/formats/object_detection/anchor_pb2.py
mediapipe/framework/formats/object_detection/__init__.py
mediapipe/framework/tool/calculator_graph_template_pb2.py
mediapipe/framework/tool/node_chain_subgraph_pb2.py
mediapipe/framework/tool/packet_generator_wrapper_calculator_pb2.py
mediapipe/framework/tool/field_data_pb2.py
mediapipe/framework/tool/switch_container_pb2.py
mediapipe/framework/tool/__init__.py
mediapipe/framework/tool/source_pb2.py
mediapipe/framework/deps/proto_descriptor_pb2.py
mediapipe/framework/deps/__init__.py
